{"chunk_definitions":[{"row":77,"row_count":1,"visible":true,"expansion_state":0,"options":{"engine":"r","label":"simulation","fig.width":10,"fig.height":4},"document_id":"AC972953","chunk_id":"cpktom5t211jm","chunk_label":"simulation"},{"row":93,"row_count":1,"visible":true,"expansion_state":0,"options":{"engine":"r","label":"fit","cache":true},"document_id":"AC972953","chunk_id":"ciuggyxxdwnui","chunk_label":"fit"},{"row":112,"row_count":1,"visible":true,"expansion_state":0,"options":{"engine":"r","label":"pred","fig.width":10,"fig.height":4},"document_id":"AC972953","chunk_id":"cfty1w40cx0eo","chunk_label":"pred"}],"doc_write_time":1630623350,"chunk_rendered_width":400}